vbart/Dockerfile
vbart/__init__.py
vbart/app.py
vbart/backup.py
vbart/backups.py
vbart/classes.py
vbart/constants.py
vbart/null.py
vbart/parsers/__init__.py
vbart/parsers/backup_args.py
vbart/parsers/backups_args.py
vbart/parsers/refresh_args.py
vbart/parsers/restore_args.py
vbart/py.typed
vbart/refresh.py
vbart/restore.py
vbart/utilities.py
vbart-0.1.8.dist-info/WHEEL
vbart-0.1.8.dist-info/entry_points.txt
vbart-0.1.8.dist-info/METADATA
vbart-0.1.8.dist-info/RECORD
