Metadata-Version: 2.3
Name: vbart
Version: 0.1.8
Summary: Volume Backup And Restoration Tool for Docker
Keywords: archive,backup,compose,compress,compression,docker,restore,vbart,volume,volumes
Author: Peter Nardi
Author-email: Peter Nardi <pete@nardi.com>
License: MIT License
Classifier: Development Status :: 4 - Beta
Classifier: Intended Audience :: Developers
Classifier: Intended Audience :: Information Technology
Classifier: Intended Audience :: System Administrators
Classifier: License :: OSI Approved :: MIT License
Classifier: Natural Language :: English
Classifier: Operating System :: OS Independent
Classifier: Programming Language :: Python :: 3
Classifier: Programming Language :: Python :: 3.9
Classifier: Programming Language :: Python :: 3.10
Classifier: Programming Language :: Python :: 3.11
Classifier: Programming Language :: Python :: 3.12
Classifier: Programming Language :: Python :: 3.13
Classifier: Topic :: System :: Archiving :: Backup
Classifier: Topic :: System :: Archiving :: Compression
Classifier: Topic :: Utilities
Requires-Dist: docker>=7.1.0
Requires-Dist: vbart
Maintainer: Peter Nardi
Maintainer-email: Peter Nardi <pete@nardi.com>
Requires-Python: >=3.9
Project-URL: Bug Tracker, https://github.com/geozeke/vbart/issues
Project-URL: Source Code, https://github.com/geozeke/vbart
